click_lazy/__init__.py
click_lazy-0.0.1.dist-info/LICENSE
click_lazy-0.0.1.dist-info/METADATA
click_lazy-0.0.1.dist-info/WHEEL
click_lazy-0.0.1.dist-info/top_level.txt
click_lazy-0.0.1.dist-info/RECORD
